{
  "project_info": {
    "project_number": "629088905005",
    "project_id": "bionic-water-366401",
    "storage_bucket": "bionic-water-366401.appspot.com"
  },
  "client": [
    {
      "client_info": {
        "mobilesdk_app_id": "1:629088905005:android:4673593161291f9fe015a4",
        "android_client_info": {
          "package_name": "world.verifi.app"
        }
      },
      "oauth_client": [
        {
          "client_id": "629088905005-qfl72u3t5qu43rf0cdvl45vcsgn0iefd.apps.googleusercontent.com",
          "client_type": 1,
          "android_info": {
            "package_name": "world.verifi.app",
            "certificate_hash": "bf7a74f0969ad89d331feaf82d0d2a82441ffeea"
          }
        },
        {
          "client_id": "629088905005-sd9r8h9onbu94dsput4o4vh1dffbqu3p.apps.googleusercontent.com",
          "client_type": 1,
          "android_info": {
            "package_name": "world.verifi.app",
            "certificate_hash": "59c7b3e5dedb405937448e4ec2194818bcad074b"
          }
        },
        {
          "client_id": "629088905005-ulu7d9d6133nl5rnb3n0aq78qglsqf5n.apps.googleusercontent.com",
          "client_type": 1,
          "android_info": {
            "package_name": "world.verifi.app",
            "certificate_hash": "e13a4a65602e31b77faea9173bdab97a77d83e95"
          }
        },
        {
          "client_id": "629088905005-8n510m54vcmn4akckvf9lv59b4dr7u7m.apps.googleusercontent.com",
          "client_type": 3
        }
      ],
      "api_key": [
        {
          "current_key": "AIzaSyA8BzRbnT-JXpFtyYdPzOAtBVEmz14OqXc"
        }
      ],
      "services": {
        "appinvite_service": {
          "other_platform_oauth_client": [
            {
              "client_id": "629088905005-8n510m54vcmn4akckvf9lv59b4dr7u7m.apps.googleusercontent.com",
              "client_type": 3
            },
            {
              "client_id": "629088905005-9l4vt43sp337ne7nq2arsnvmmb2vccrt.apps.googleusercontent.com",
              "client_type": 2,
              "ios_info": {
                "bundle_id": "world.verifi.app"
              }
            }
          ]
        }
      }
    }
  ],
  "configuration_version": "1"
}